MANIFEST.in
pybtctool
setup.py
bitcointools/__init__.py
bitcointools/bci.py
bitcointools/blocks.py
bitcointools/composite.py
bitcointools/deterministic.py
bitcointools/english.txt
bitcointools/main.py
bitcointools/mnemonic.py
bitcointools/py2specials.py
bitcointools/py3specials.py
bitcointools/ripemd.py
bitcointools/stealth.py
bitcointools/transaction.py
bitcointools.egg-info/PKG-INFO
bitcointools.egg-info/SOURCES.txt
bitcointools.egg-info/dependency_links.txt
bitcointools.egg-info/top_level.txt