Metadata-Version: 1.0
Name: bitcointools
Version: 1.1.44
Summary: Python Bitcoin Tools
Home-page: http://github.com/vbuterin/pybitcointools
Author: Vitalik Buterin
Author-email: vbuterin@gmail.com
License: UNKNOWN
Platform: UNKNOWN
